<?xml version="1.0" encoding="utf-8"?>
<TextureAtlas imagePath="bg bop.png">
	<!-- Created with Adobe Animate version 21.0.2.37893 -->
	<!-- http://www.adobe.com/products/animate.html -->
	<SubTexture name="bg bop0000" x="0" y="0" width="772" height="642" frameX="0" frameY="-26" frameWidth="772" frameHeight="668"/>
	<SubTexture name="bg bop0001" x="772" y="0" width="772" height="642" frameX="0" frameY="-26" frameWidth="772" frameHeight="668"/>
	<SubTexture name="bg bop0002" x="0" y="642" width="769" height="652" frameX="-3" frameY="-16" frameWidth="772" frameHeight="668"/>
	<SubTexture name="bg bop0003" x="769" y="642" width="769" height="652" frameX="-3" frameY="-16" frameWidth="772" frameHeight="668"/>
	<SubTexture name="bg bop0004" x="0" y="1294" width="758" height="668" frameX="-14" frameY="0" frameWidth="772" frameHeight="668"/>
	<SubTexture name="bg bop0005" x="0" y="1294" width="758" height="668" frameX="-14" frameY="0" frameWidth="772" frameHeight="668"/>
	<SubTexture name="bg bop0006" x="0" y="1294" width="758" height="668" frameX="-14" frameY="0" frameWidth="772" frameHeight="668"/>
	<SubTexture name="bg bop0007" x="0" y="1294" width="758" height="668" frameX="-14" frameY="0" frameWidth="772" frameHeight="668"/>
	<SubTexture name="bg bop0008" x="0" y="1294" width="758" height="668" frameX="-14" frameY="0" frameWidth="772" frameHeight="668"/>
	<SubTexture name="bg bop0009" x="0" y="1294" width="758" height="668" frameX="-14" frameY="0" frameWidth="772" frameHeight="668"/>
	<SubTexture name="bg bop0010" x="0" y="1294" width="758" height="668" frameX="-14" frameY="0" frameWidth="772" frameHeight="668"/>
	<SubTexture name="bg bop0011" x="0" y="1294" width="758" height="668" frameX="-14" frameY="0" frameWidth="772" frameHeight="668"/>
	<SubTexture name="bg bop0012" x="0" y="1294" width="758" height="668" frameX="-14" frameY="0" frameWidth="772" frameHeight="668"/>
	<SubTexture name="bg bop0013" x="0" y="1294" width="758" height="668" frameX="-14" frameY="0" frameWidth="772" frameHeight="668"/>
</TextureAtlas>
